pydytuesday/__init__.py
pydytuesday/__main__.py
pydytuesday-0.1.2.dist-info/METADATA
pydytuesday-0.1.2.dist-info/WHEEL
pydytuesday-0.1.2.dist-info/entry_points.txt
pydytuesday-0.1.2.dist-info/licenses/LICENSE
pydytuesday-0.1.2.dist-info/RECORD
