Metadata-Version: 2.4
Name: pydytuesday
Version: 0.1.2
Summary: A Python port of the TidyTuesday Downloader
Author-email: Andreas Varotsis <andreas.varotsis@gmail.com>
License-File: LICENSE
Requires-Python: >=3.10
Requires-Dist: beautifulsoup4>=4.13.3
Requires-Dist: markdown>=3.7
Requires-Dist: pandas>=2.2.3
Requires-Dist: pytz>=2025.1
Requires-Dist: requests>=2.32.3
